Perceptron/__init__.py
Perceptron/perceptron.py
PyPerceptron-1.0.1.dist-info/License
PyPerceptron-1.0.1.dist-info/METADATA
PyPerceptron-1.0.1.dist-info/WHEEL
PyPerceptron-1.0.1.dist-info/top_level.txt
PyPerceptron-1.0.1.dist-info/RECORD
